{
 "package-id" : "fhir.nl.gf",
 "title" : "NL Generic Functions IG", 
 "canonical" : "http://nuts-foundation.github.io/nl-generic-functions-ig", 
 "introduction" : "The introduction that should appear in the FHIR IG registry",
 "list" : [{
  "version" : "current",
  "desc" : "Continuous Integration Build (latest in version control)",
  "path" : "http://nuts-foundation.github.io/nl-generic-functions-ig/ImplementationGuide/fhir.nl.gf",
  "status" : "ci-build",
  "current" : true
 },{
  "version" : "0.1.0",  
  "date" : "2025-08-29", 
  "desc" : "Initial STU ballot (Mmm yyyy Ballot)",   
  "path" : "http://hl7.org/fhir/yyyyMmm/myig.html",   
  "status" : "ballot",   
  "sequence" : "DSTU 1"
 }]
}